db_env/__init__.py
db_env/create_env.py
db_env/insert_data.py
db_env/select_data.py
db_env-0.4.2.dist-info/METADATA
db_env-0.4.2.dist-info/WHEEL
db_env-0.4.2.dist-info/top_level.txt
db_env-0.4.2.dist-info/RECORD
