Metadata-Version: 2.1
Name: db_env
Version: 0.4.2
Summary: Creating relational databases with SQLite but easier. More information follows.
Author: Daniel Huber
Requires-Dist: pandas
